{
  "nodes": [
    {
      "id": "episode:6LutKv6Ooy8",
      "type": "episode",
      "label": "From Labor Arbitrage to Agent Bosses",
      "index": 1,
      "video_id": "6LutKv6Ooy8"
    },
    {
      "id": "episode:LLdfdtNffuY",
      "type": "episode",
      "label": "The Human Disadvantage | A Free Audiobook for Professionals Navigating AI",
      "index": 2,
      "video_id": "LLdfdtNffuY"
    },
    {
      "id": "episode:GsvgR29ml1U",
      "type": "episode",
      "label": "Personas Chapter 8 The Human Disadvantage",
      "index": 3,
      "video_id": "GsvgR29ml1U"
    },
    {
      "id": "episode:zMvUfZJ_a3E",
      "type": "episode",
      "label": "AI Layoffs, Forced Rankings, and the Cost of Fear",
      "index": 4,
      "video_id": "zMvUfZJ_a3E"
    },
    {
      "id": "episode:GUEqT-nY2o0",
      "type": "episode",
      "label": "When AI Fakes Reality, Who Do We Trust",
      "index": 5,
      "video_id": "GUEqT-nY2o0"
    },
    {
      "id": "episode:sJL-9LIgSz4",
      "type": "episode",
      "label": "What If AI Made You More Valuable, Not Less?",
      "index": 6,
      "video_id": "sJL-9LIgSz4"
    },
    {
      "id": "episode:b4kdK5EaTKA",
      "type": "episode",
      "label": "From Experience to Infinite Leverage | An Audio Book for Professionals",
      "index": 7,
      "video_id": "b4kdK5EaTKA"
    },
    {
      "id": "episode:hTv9MG3KOyo",
      "type": "episode",
      "label": "The Agentic Insider: When AI Becomes the Threat Inside Your Organization | Full Audiobook",
      "index": 8,
      "video_id": "hTv9MG3KOyo"
    },
    {
      "id": "episode:lnHWXgVgicY",
      "type": "episode",
      "label": "AI Phishing en de Onwetende Geldezel",
      "index": 9,
      "video_id": "lnHWXgVgicY"
    },
    {
      "id": "episode:5CO_guu0RvA",
      "type": "episode",
      "label": "Agentic AI in the Corporate Arena",
      "index": 10,
      "video_id": "5CO_guu0RvA"
    },
    {
      "id": "episode:ucjz89rxM7w",
      "type": "episode",
      "label": "Why AI Is Becoming a National Security Issue",
      "index": 11,
      "video_id": "ucjz89rxM7w"
    },
    {
      "id": "episode:dPDxVhefcHU",
      "type": "episode",
      "label": "The Career Survival Guide for the AI Era | Full Audiobook",
      "index": 12,
      "video_id": "dPDxVhefcHU"
    },
    {
      "id": "episode:0PmEqipqaPw",
      "type": "episode",
      "label": "AI and the Growth Paradox at Work",
      "index": 13,
      "video_id": "0PmEqipqaPw"
    },
    {
      "id": "episode:rv9X_Zm2Ndw",
      "type": "episode",
      "label": "Club Genius: What Extraordinary Leaders Know That Most Organizations Miss (Full Audiobook)",
      "index": 14,
      "video_id": "rv9X_Zm2Ndw"
    },
    {
      "id": "episode:U7-cKoIv9Nw",
      "type": "episode",
      "label": "The Day the Insider Stopped Being Human",
      "index": 15,
      "video_id": "U7-cKoIv9Nw"
    },
    {
      "id": "episode:3oL3KUwkqkw",
      "type": "episode",
      "label": "Agentic AI and the Swarm Attack Era",
      "index": 16,
      "video_id": "3oL3KUwkqkw"
    },
    {
      "id": "episode:kAbsP1c8skg",
      "type": "episode",
      "label": "They Didn't Announce Layoffs. They Made People Leave.",
      "index": 17,
      "video_id": "kAbsP1c8skg"
    },
    {
      "id": "episode:QJMqlrQlHt4",
      "type": "episode",
      "label": "When Your Coworker Is Actually AI",
      "index": 18,
      "video_id": "QJMqlrQlHt4"
    },
    {
      "id": "episode:_l9sxTRmZVs",
      "type": "episode",
      "label": "AI at ang Kinabukasan ng BPO ng Pilipinas",
      "index": 19,
      "video_id": "_l9sxTRmZVs"
    },
    {
      "id": "episode:F_BnwSTrmsU",
      "type": "episode",
      "label": "Why AI Needs a Council, Not a King",
      "index": 20,
      "video_id": "F_BnwSTrmsU"
    },
    {
      "id": "episode:QjWiBFkOEIY",
      "type": "episode",
      "label": "The Death of the Dossier  Defending Reality Against AI Swarms",
      "index": 21,
      "video_id": "QjWiBFkOEIY"
    },
    {
      "id": "episode:f-zxpA2iNlA",
      "type": "episode",
      "label": "When AI Becomes the Workplace Lie Detector 1",
      "index": 22,
      "video_id": "f-zxpA2iNlA"
    },
    {
      "id": "episode:Lt3dTPM-xtw",
      "type": "episode",
      "label": "La IA est\u00e1 borrando el primer escal\u00f3n laboral",
      "index": 23,
      "video_id": "Lt3dTPM-xtw"
    },
    {
      "id": "episode:VwznSiRvYR8",
      "type": "episode",
      "label": "When AI Outruns Human Judgment",
      "index": 24,
      "video_id": "VwznSiRvYR8"
    },
    {
      "id": "episode:zxUfl7UyduE",
      "type": "episode",
      "label": "Humanoid Robots and the Labor Shortage That\u2019s Reshaping Work",
      "index": 25,
      "video_id": "zxUfl7UyduE"
    },
    {
      "id": "episode:RvF039WQ_wA",
      "type": "episode",
      "label": "Agentes Digitais e o Futuro do Trabalho Luso\u0301fono",
      "index": 26,
      "video_id": "RvF039WQ_wA"
    },
    {
      "id": "episode:EPb-vfo9vWw",
      "type": "episode",
      "label": "When AI Becomes Too Powerful to Ship",
      "index": 27,
      "video_id": "EPb-vfo9vWw"
    },
    {
      "id": "episode:4VdZKLEdlR4",
      "type": "episode",
      "label": "AI Skill Libraries  The Next Layer of Enterprise Intelligence",
      "index": 28,
      "video_id": "4VdZKLEdlR4"
    },
    {
      "id": "episode:iL-finalN_c",
      "type": "episode",
      "label": "When AI Agents Go Rogue  Prompt Injection and Oversight",
      "index": 29,
      "video_id": "iL-finalN_c"
    },
    {
      "id": "episode:eA-mdZM8Sgc",
      "type": "episode",
      "label": "Work  Centaurs, Cyborgs, and the Perils of Trust",
      "index": 30,
      "video_id": "eA-mdZM8Sgc"
    },
    {
      "id": "episode:LClaFOXtW7c",
      "type": "episode",
      "label": "Work and the Rise of Autonomous AI Agents",
      "index": 31,
      "video_id": "LClaFOXtW7c"
    },
    {
      "id": "episode:TNSMkBDKbgI",
      "type": "episode",
      "label": "The 2026 AI Compliance Crunch  When Every Prompt Becomes Evidence",
      "index": 32,
      "video_id": "TNSMkBDKbgI"
    },
    {
      "id": "episode:17S4jmPV6Y8",
      "type": "episode",
      "label": "Humanos en la Era de la IA  El Verdadero Factor Diferencial",
      "index": 33,
      "video_id": "17S4jmPV6Y8"
    },
    {
      "id": "episode:0gRQYUBSweU",
      "type": "episode",
      "label": "The Silicon Sieve  AI and the Future of Financial Crime Detection",
      "index": 34,
      "video_id": "0gRQYUBSweU"
    },
    {
      "id": "episode:2KNcMSKYkpY",
      "type": "episode",
      "label": "AI Counterintelligence, Deepfakes, and the End of Anonymity",
      "index": 35,
      "video_id": "2KNcMSKYkpY"
    },
    {
      "id": "episode:fhyTFqyptMo",
      "type": "episode",
      "label": "Europe\u2019s AI Rulebook  Bias, Surveillance, and the Brussels Effect",
      "index": 36,
      "video_id": "fhyTFqyptMo"
    },
    {
      "id": "episode:U4Q5zbpvN9I",
      "type": "episode",
      "label": "AI sem pessoas n\u00e3o gera lucro",
      "index": 37,
      "video_id": "U4Q5zbpvN9I"
    },
    {
      "id": "episode:w3-Tj3rtXi8",
      "type": "episode",
      "label": "AI Counterintelligence, Deepfakes, and the End of Anonymity",
      "index": 38,
      "video_id": "w3-Tj3rtXi8"
    },
    {
      "id": "episode:u9N7w_tmC0s",
      "type": "episode",
      "label": "AI Hype, Corporate Narratives, and the Human Workforce",
      "index": 39,
      "video_id": "u9N7w_tmC0s"
    },
    {
      "id": "episode:R37YkMPW3QI",
      "type": "episode",
      "label": "Shadow AI: The Silent Revolution Transforming Work Before Leaders Notice",
      "index": 40,
      "video_id": "R37YkMPW3QI"
    },
    {
      "id": "episode:RzHHYmV40dE",
      "type": "episode",
      "label": "AI Red Teams  How Agentic AI Thinks Like an Attacker",
      "index": 41,
      "video_id": "RzHHYmV40dE"
    },
    {
      "id": "episode:62TkirkF4p0",
      "type": "episode",
      "label": "Course 3   Understanding AI Governance and the AIGP Certification",
      "index": 42,
      "video_id": "62TkirkF4p0"
    },
    {
      "id": "episode:LivL91WaFqk",
      "type": "episode",
      "label": "AI Layoffs Don\u2019t Boost Profits  The Human Advantage 1",
      "index": 43,
      "video_id": "LivL91WaFqk"
    },
    {
      "id": "episode:-zCdDx1kHrw",
      "type": "episode",
      "label": "When AI Sounds Panicked or confused, Humans Start Believing It",
      "index": 44,
      "video_id": "-zCdDx1kHrw"
    },
    {
      "id": "episode:fUqJZLC2GL4",
      "type": "episode",
      "label": "From Logins to Corporate-Espionage  AI, Deepfakes, and Zero Trust",
      "index": 45,
      "video_id": "fUqJZLC2GL4"
    },
    {
      "id": "episode:bpoa5WKDbys",
      "type": "episode",
      "label": "A Voice First AI Revolution",
      "index": 46,
      "video_id": "bpoa5WKDbys"
    },
    {
      "id": "episode:UH_Z81xiFBs",
      "type": "episode",
      "label": "AI Boom or Bubble  The Human Future at Risk",
      "index": 47,
      "video_id": "UH_Z81xiFBs"
    },
    {
      "id": "episode:TlOCqT6e2Ps",
      "type": "episode",
      "label": "The AI Control Problem",
      "index": 48,
      "video_id": "TlOCqT6e2Ps"
    },
    {
      "id": "episode:0EJvLkTX6G8",
      "type": "episode",
      "label": "Ethics as a Termination Strategy",
      "index": 49,
      "video_id": "0EJvLkTX6G8"
    },
    {
      "id": "episode:MBYm8fEPOqY",
      "type": "episode",
      "label": "From AI Pilots to Autonomous Enterprise",
      "index": 50,
      "video_id": "MBYm8fEPOqY"
    },
    {
      "id": "episode:s-8EteJ57lU",
      "type": "episode",
      "label": "When AI Makes Scams Look Legit",
      "index": 51,
      "video_id": "s-8EteJ57lU"
    },
    {
      "id": "episode:YXxf_3euA8c",
      "type": "episode",
      "label": "The Trillion Dollar AI Reality Check",
      "index": 52,
      "video_id": "YXxf_3euA8c"
    },
    {
      "id": "episode:FTbl2wMeZj4",
      "type": "episode",
      "label": "AI Won\u2019t Replace Engineers\u2014It Raises the Stakes",
      "index": 53,
      "video_id": "FTbl2wMeZj4"
    },
    {
      "id": "episode:OrDPW3gIN9M",
      "type": "episode",
      "label": "Layered Down  How Reorgs Quietly Demote Teams",
      "index": 54,
      "video_id": "OrDPW3gIN9M"
    },
    {
      "id": "episode:0km1iTMPCPE",
      "type": "episode",
      "label": "The Regret Curve  When AI Replaces Too Much, Too Fast",
      "index": 55,
      "video_id": "0km1iTMPCPE"
    },
    {
      "id": "episode:JvjiFLdYQQY",
      "type": "episode",
      "label": "When AI Stops Waiting  The Rise of Synthetic Workforces",
      "index": 56,
      "video_id": "JvjiFLdYQQY"
    },
    {
      "id": "episode:bKeXvlTfV48",
      "type": "episode",
      "label": "When AI Stops Assisting and Starts Deciding",
      "index": 57,
      "video_id": "bKeXvlTfV48"
    },
    {
      "id": "episode:G9hOJyWPCic",
      "type": "episode",
      "label": "The Catastrophe Gap  - Navigating the Limits of AI Control",
      "index": 58,
      "video_id": "G9hOJyWPCic"
    },
    {
      "id": "episode:-wq06zD82pw",
      "type": "episode",
      "label": "AI Is Replacing the Corporate Middle",
      "index": 59,
      "video_id": "-wq06zD82pw"
    },
    {
      "id": "episode:6TIGl_8KWOY",
      "type": "episode",
      "label": "When Workers Become Training Data",
      "index": 60,
      "video_id": "6TIGl_8KWOY"
    },
    {
      "id": "episode:PyM_VqDmNp8",
      "type": "episode",
      "label": "The AI Layoff Trap  Why Over Automation Hurts Everyone",
      "index": 61,
      "video_id": "PyM_VqDmNp8"
    },
    {
      "id": "episode:E5KnDgkwXUQ",
      "type": "episode",
      "label": "Inside the AI Driven Insider Threat",
      "index": 62,
      "video_id": "E5KnDgkwXUQ"
    },
    {
      "id": "episode:2meHM8VYi1M",
      "type": "episode",
      "label": "Autonomous Trucks and the New Freight Economy",
      "index": 63,
      "video_id": "2meHM8VYi1M"
    },
    {
      "id": "episode:c2OzsCzHDlk",
      "type": "episode",
      "label": "AI Needs Control, Not Blind Trust",
      "index": 64,
      "video_id": "c2OzsCzHDlk"
    },
    {
      "id": "episode:2atqsFo4Wao",
      "type": "episode",
      "label": "Mythos  The Operational Risk Hiding in AI",
      "index": 65,
      "video_id": "2atqsFo4Wao"
    },
    {
      "id": "episode:s7Xy_si7Ql0",
      "type": "episode",
      "label": "AI Cover Stories and the Liability Loophole",
      "index": 66,
      "video_id": "s7Xy_si7Ql0"
    },
    {
      "id": "episode:6eq9tYFCjkY",
      "type": "episode",
      "label": "The Algorithmic Gatekeeper  When AI Rejects You First",
      "index": 67,
      "video_id": "6eq9tYFCjkY"
    },
    {
      "id": "episode:IKbzy-7AaU4",
      "type": "episode",
      "label": "When AI Starts Training on Its Own Echo",
      "index": 68,
      "video_id": "IKbzy-7AaU4"
    },
    {
      "id": "episode:97coLf7y-TE",
      "type": "episode",
      "label": "When AI Replaces Managers, What Gets Lost",
      "index": 69,
      "video_id": "97coLf7y-TE"
    },
    {
      "id": "episode:9XrDuutuymw",
      "type": "episode",
      "label": "How Files and Search Engines Quietly Leak Secrets",
      "index": 70,
      "video_id": "9XrDuutuymw"
    },
    {
      "id": "episode:i403KVAk1i8",
      "type": "episode",
      "label": "AEON and the Quiet Factory Revolution",
      "index": 71,
      "video_id": "i403KVAk1i8"
    },
    {
      "id": "episode:TWXgYeA-dUQ",
      "type": "episode",
      "label": "The Great AI Career Shuffle  Who Moves Up, Who Gets Left Out",
      "index": 72,
      "video_id": "TWXgYeA-dUQ"
    },
    {
      "id": "episode:dj09CoXr_d4",
      "type": "episode",
      "label": "The Comfort Illusion  Why Workers Don\u2019t Fear AI",
      "index": 73,
      "video_id": "dj09CoXr_d4"
    },
    {
      "id": "episode:WMyGdjk5pKk",
      "type": "episode",
      "label": "The Ethical Debt of Moving Too Fast",
      "index": 74,
      "video_id": "WMyGdjk5pKk"
    },
    {
      "id": "episode:gb4BKeB6LZU",
      "type": "episode",
      "label": "Your Work Is Being Measured in the Shadows",
      "index": 75,
      "video_id": "gb4BKeB6LZU"
    },
    {
      "id": "episode:JINcd7RWujk",
      "type": "episode",
      "label": "Digital Subversion  How AI Pollutes the Public Well",
      "index": 76,
      "video_id": "JINcd7RWujk"
    },
    {
      "id": "episode:_4Cayu-GHMc",
      "type": "episode",
      "label": "When AI Efficiency Becomes an Automation Arms Race",
      "index": 77,
      "video_id": "_4Cayu-GHMc"
    },
    {
      "id": "episode:Jh6tSkJ8JCk",
      "type": "episode",
      "label": "Why Agentic AI Makes Workers Feel Replaceable",
      "index": 78,
      "video_id": "Jh6tSkJ8JCk"
    },
    {
      "id": "episode:SAnjXK_2CiQ",
      "type": "episode",
      "label": "Human in the Loop or Just a Rubber Stamp",
      "index": 79,
      "video_id": "SAnjXK_2CiQ"
    },
    {
      "id": "episode:U0FUsBI2FrQ",
      "type": "episode",
      "label": "From Admin Tasks to Superwoman AI Orchestrator",
      "index": 80,
      "video_id": "U0FUsBI2FrQ"
    },
    {
      "id": "episode:ohGCQ52QUdE",
      "type": "episode",
      "label": "AI at Machine Speed  The Cybersecurity Tipping Point",
      "index": 81,
      "video_id": "ohGCQ52QUdE"
    },
    {
      "id": "episode:zf3lDP3Wqis",
      "type": "episode",
      "label": "Embedded AI, Not AI Chaos",
      "index": 82,
      "video_id": "zf3lDP3Wqis"
    },
    {
      "id": "episode:MX1T7ov-PoA",
      "type": "episode",
      "label": "When AI Becomes Infrastructure",
      "index": 83,
      "video_id": "MX1T7ov-PoA"
    },
    {
      "id": "episode:9IWCMxVDM-o",
      "type": "episode",
      "label": "The Great Job Illusion  Why Hiring Feels Fake",
      "index": 84,
      "video_id": "9IWCMxVDM-o"
    },
    {
      "id": "episode:EVVZGQ-EZ-4",
      "type": "episode",
      "label": "From Schlitz to AI  When Efficiency Eats Trust",
      "index": 85,
      "video_id": "EVVZGQ-EZ-4"
    },
    {
      "id": "episode:p8J1bP8bO6Q",
      "type": "episode",
      "label": "Why the Company Deal Is Breaking and the Rise of Sovereign Specialists",
      "index": 86,
      "video_id": "p8J1bP8bO6Q"
    },
    {
      "id": "episode:K0Yla0SjXpM",
      "type": "episode",
      "label": "The Bank That Never Sleeps  AI, Risk, and Compliance at Machine Speed",
      "index": 87,
      "video_id": "K0Yla0SjXpM"
    },
    {
      "id": "episode:CR-95TPthDE",
      "type": "episode",
      "label": "The Cost of Silence at Work",
      "index": 88,
      "video_id": "CR-95TPthDE"
    },
    {
      "id": "episode:wXtvQ2Y1oek",
      "type": "episode",
      "label": "When Chatbots Become Validators of Harm",
      "index": 89,
      "video_id": "wXtvQ2Y1oek"
    },
    {
      "id": "episode:IN37dOTQ-FI",
      "type": "episode",
      "label": "Why the 10x Engineer Myth Is Breaking Down",
      "index": 90,
      "video_id": "IN37dOTQ-FI"
    },
    {
      "id": "episode:SqbkPfa1L6U",
      "type": "episode",
      "label": "The AI Bubble Playbook  Hype, Judgment, and Hidden Labor",
      "index": 91,
      "video_id": "SqbkPfa1L6U"
    },
    {
      "id": "episode:xihtVFCn16o",
      "type": "episode",
      "label": "When Logging In Becomes the New Breaking In",
      "index": 92,
      "video_id": "xihtVFCn16o"
    },
    {
      "id": "episode:SS3As5XrviA",
      "type": "episode",
      "label": "Lipstick on a Pig  Why Polish Can Hide Weakness",
      "index": 93,
      "video_id": "SS3As5XrviA"
    },
    {
      "id": "episode:ewa5H9gvaCM",
      "type": "episode",
      "label": "AI\u2019s Gray Rhinos and Black Swans",
      "index": 94,
      "video_id": "ewa5H9gvaCM"
    },
    {
      "id": "episode:VT3PSbBl5SE",
      "type": "episode",
      "label": "When Automation Cuts Costs and Customers",
      "index": 95,
      "video_id": "VT3PSbBl5SE"
    },
    {
      "id": "episode:RhOYvEfmxik",
      "type": "episode",
      "label": "AI vs  Money Laundering  Stopping Cash Before It Vanishes",
      "index": 96,
      "video_id": "RhOYvEfmxik"
    },
    {
      "id": "episode:8tYypLMXRbo",
      "type": "episode",
      "label": "Why AI Needs More Humans (to watch it)",
      "index": 97,
      "video_id": "8tYypLMXRbo"
    },
    {
      "id": "episode:h3tc5tSjcZI",
      "type": "episode",
      "label": "Polished Fiction  When AI Sounds Right but Isn\u2019t",
      "index": 98,
      "video_id": "h3tc5tSjcZI"
    },
    {
      "id": "episode:zy2Z2d5p92k",
      "type": "episode",
      "label": "AI Exposes Weak Leadership, It Doesn\u2019t Fix It",
      "index": 99,
      "video_id": "zy2Z2d5p92k"
    },
    {
      "id": "episode:8oLkHGX-FyA",
      "type": "episode",
      "label": "When AI Becomes The Default Voice",
      "index": 100,
      "video_id": "8oLkHGX-FyA"
    },
    {
      "id": "episode:Vnx4xogxBAU",
      "type": "episode",
      "label": "When Work Gets Quieter but Pressure Gets Louder",
      "index": 101,
      "video_id": "Vnx4xogxBAU"
    },
    {
      "id": "episode:Snggc24tXwk",
      "type": "episode",
      "label": "When High Performance Turns Into A Conduct Case",
      "index": 102,
      "video_id": "Snggc24tXwk"
    },
    {
      "id": "episode:1UhZ4HVe70I",
      "type": "episode",
      "label": "The Autonomous Employee When AI Starts Doing the Work",
      "index": 103,
      "video_id": "1UhZ4HVe70I"
    },
    {
      "id": "episode:IfKmWHZKs0o",
      "type": "episode",
      "label": "AI Confidence Is an Illusion",
      "index": 104,
      "video_id": "IfKmWHZKs0o"
    },
    {
      "id": "episode:8UtrZsxhiPw",
      "type": "episode",
      "label": "Regulating AI in Real Time SupTech and Oversight",
      "index": 105,
      "video_id": "8UtrZsxhiPw"
    },
    {
      "id": "episode:1BBo4Tnqc58",
      "type": "episode",
      "label": "When AI Starts Thinking For You",
      "index": 106,
      "video_id": "1BBo4Tnqc58"
    },
    {
      "id": "episode:4RRRPfDAShA",
      "type": "episode",
      "label": "How to Land Work You\u2019ll Actually Love",
      "index": 107,
      "video_id": "4RRRPfDAShA"
    },
    {
      "id": "episode:G1ZJKw-JXsc",
      "type": "episode",
      "label": "AgenticAI  From Chatbots to Digital Teammates",
      "index": 108,
      "video_id": "G1ZJKw-JXsc"
    },
    {
      "id": "episode:zQbiq710ciw",
      "type": "episode",
      "label": "Over Skis Leadership: Proximity, Power, and the Human Cost of Shallow Management",
      "index": 109,
      "video_id": "zQbiq710ciw"
    },
    {
      "id": "episode:RwYrz1L87iw",
      "type": "episode",
      "label": "AI Paradox  Why We Use It but Don\u2019t Trust It",
      "index": 110,
      "video_id": "RwYrz1L87iw"
    },
    {
      "id": "episode:qb9rJivuveU",
      "type": "episode",
      "label": "How Bad Leadership Turns Teams Toxic",
      "index": 111,
      "video_id": "qb9rJivuveU"
    },
    {
      "id": "episode:EponVCbI1w8",
      "type": "episode",
      "label": "When the Workplace Goes Quiet",
      "index": 112,
      "video_id": "EponVCbI1w8"
    },
    {
      "id": "episode:2zK5fLQohO8",
      "type": "episode",
      "label": "The Vanishing Apprenticeship:  What Happens When AI Learns the Job Before People Do.",
      "index": 113,
      "video_id": "2zK5fLQohO8"
    },
    {
      "id": "episode:Z-QgJu7EMZY",
      "type": "episode",
      "label": "Harder to Replace  The New Rules of Job Security",
      "index": 114,
      "video_id": "Z-QgJu7EMZY"
    },
    {
      "id": "episode:c76N8NVr-c8",
      "type": "episode",
      "label": "The Ghost of GE  How Old School Rank and Yank Still Haunts Work Culture",
      "index": 115,
      "video_id": "c76N8NVr-c8"
    },
    {
      "id": "episode:Pq21DxO_hIU",
      "type": "episode",
      "label": "When Healthcare Efficiency Turns Cold",
      "index": 116,
      "video_id": "Pq21DxO_hIU"
    },
    {
      "id": "episode:ykBfA9UYIMg",
      "type": "episode",
      "label": "Welcome to The Human Workforce",
      "index": 117,
      "video_id": "ykBfA9UYIMg"
    },
    {
      "id": "episode:eJxaxyRyPdk",
      "type": "episode",
      "label": "The First Real AI That Worked Against Humans",
      "index": 118,
      "video_id": "eJxaxyRyPdk"
    },
    {
      "id": "episode:PPTI2yKN9R8",
      "type": "episode",
      "label": "AI Work and the New Human Advantage",
      "index": 119,
      "video_id": "PPTI2yKN9R8"
    },
    {
      "id": "episode:vHKnqz6nDcY",
      "type": "episode",
      "label": "Episode 6  The Job You Already Have Is the One They\u2019re Replacing\u2014Unless You Change First",
      "index": 120,
      "video_id": "vHKnqz6nDcY"
    },
    {
      "id": "episode:xMOwbE4xQOY",
      "type": "episode",
      "label": "The AI Illusion  Why Companies Are Getting It Dangerously Wrong",
      "index": 121,
      "video_id": "xMOwbE4xQOY"
    },
    {
      "id": "episode:cotQ60ULwPQ",
      "type": "episode",
      "label": "Don\u2019t Let Them Live in the Matrix",
      "index": 122,
      "video_id": "cotQ60ULwPQ"
    },
    {
      "id": "episode:GYLNUItueI8",
      "type": "episode",
      "label": "Episode 3  The Meeting Room Mirage and Strategic Spaghetti Management",
      "index": 123,
      "video_id": "GYLNUItueI8"
    },
    {
      "id": "episode:miEnnrV-jLM",
      "type": "episode",
      "label": "The Fog Machine AI Ambiguity and the Quiet Push Out.",
      "index": 124,
      "video_id": "miEnnrV-jLM"
    },
    {
      "id": "episode:0_t1wqxTMYg",
      "type": "episode",
      "label": "Leadership, Power, and the Workforce in the Age of AI",
      "index": 125,
      "video_id": "0_t1wqxTMYg"
    },
    {
      "id": "episode:ZRkiE2_1LIE",
      "type": "episode",
      "label": "Are You Still Yourself at Work?",
      "index": 126,
      "video_id": "ZRkiE2_1LIE"
    },
    {
      "id": "episode:32PEG3pSalw",
      "type": "episode",
      "label": "Dont Fear the AI Threat",
      "index": 127,
      "video_id": "32PEG3pSalw"
    },
    {
      "id": "episode:qqsEaniT650",
      "type": "episode",
      "label": "The Future Belongs to People Who Learn This",
      "index": 128,
      "video_id": "qqsEaniT650"
    },
    {
      "id": "episode:CQ6bdSnTu-4",
      "type": "episode",
      "label": "The Hidden Trait Shared by Extraordinary Leaders",
      "index": 129,
      "video_id": "CQ6bdSnTu-4"
    },
    {
      "id": "episode:1JoBDQdff8s",
      "type": "episode",
      "label": "The Job You Lose May Never Be Posted Again",
      "index": 130,
      "video_id": "1JoBDQdff8s"
    },
    {
      "id": "episode:udO-8H3__JE",
      "type": "episode",
      "label": "How Many Versions of Yourself Exist at Work?",
      "index": 131,
      "video_id": "udO-8H3__JE"
    },
    {
      "id": "episode:ccBJlt_Tflo",
      "type": "episode",
      "label": "The Rise of Synthetic Media and AI Content",
      "index": 132,
      "video_id": "ccBJlt_Tflo"
    },
    {
      "id": "episode:k826P54OnVk",
      "type": "episode",
      "label": "Governing the Agentic Workforce",
      "index": 133,
      "video_id": "k826P54OnVk"
    },
    {
      "id": "episode:oNkptqgg6VY",
      "type": "episode",
      "label": "What If Experience Becomes Your Greatest Advantage?",
      "index": 134,
      "video_id": "oNkptqgg6VY"
    },
    {
      "id": "episode:XoEvGOkNtNQ",
      "type": "episode",
      "label": "Do AI Employees need to be managed?",
      "index": 135,
      "video_id": "XoEvGOkNtNQ"
    },
    {
      "id": "episode:5eWMCKKNABc",
      "type": "episode",
      "label": "Are you ready to manage AI employees?",
      "index": 136,
      "video_id": "5eWMCKKNABc"
    },
    {
      "id": "episode:mqcZCrwZ_wM",
      "type": "episode",
      "label": "Are You Ready to Manage Employees That Aren't Human",
      "index": 137,
      "video_id": "mqcZCrwZ_wM"
    },
    {
      "id": "episode:lmaGFMQd_b0",
      "type": "episode",
      "label": "Learn to Thrive working alongside of AI",
      "index": 138,
      "video_id": "lmaGFMQd_b0"
    },
    {
      "id": "episode:v6imM-nfmy0",
      "type": "episode",
      "label": "Why Some Organizations Always Win",
      "index": 139,
      "video_id": "v6imM-nfmy0"
    },
    {
      "id": "episode:cGHl9V-qvo4",
      "type": "episode",
      "label": "AI Won't Replace You. This Might.",
      "index": 140,
      "video_id": "cGHl9V-qvo4"
    },
    {
      "id": "episode:NoOzZQuUzrY",
      "type": "episode",
      "label": "Beat them at their own Game - Infinite Leverage",
      "index": 141,
      "video_id": "NoOzZQuUzrY"
    },
    {
      "id": "episode:767LRTYF4to",
      "type": "episode",
      "label": "Thrive with AI",
      "index": 142,
      "video_id": "767LRTYF4to"
    },
    {
      "id": "episode:vCd4IvacHus",
      "type": "episode",
      "label": "The Day The Insider Stopped Being Human",
      "index": 143,
      "video_id": "vCd4IvacHus"
    },
    {
      "id": "episode:Ia2DU6MU2lQ",
      "type": "episode",
      "label": "The Silent Reduction Strategy - Listen and Learn",
      "index": 144,
      "video_id": "Ia2DU6MU2lQ"
    },
    {
      "id": "episode:OOJuo5p54Ns",
      "type": "episode",
      "label": "The Agentic Insider June 2026",
      "index": 145,
      "video_id": "OOJuo5p54Ns"
    },
    {
      "id": "episode:YHqXhcVFLk0",
      "type": "episode",
      "label": "The Silent Front",
      "index": 146,
      "video_id": "YHqXhcVFLk0"
    },
    {
      "id": "episode:87QH-JQBsEg",
      "type": "episode",
      "label": "Always watch your AI",
      "index": 147,
      "video_id": "87QH-JQBsEg"
    },
    {
      "id": "episode:tYruV_XD7gw",
      "type": "episode",
      "label": "Don't leave work without The Human Workforce.",
      "index": 148,
      "video_id": "tYruV_XD7gw"
    },
    {
      "id": "episode:abb9z-xmwCQ",
      "type": "episode",
      "label": "Get Your Daily Dose of The Human Workforce",
      "index": 149,
      "video_id": "abb9z-xmwCQ"
    },
    {
      "id": "episode:VyIUAyvih28",
      "type": "episode",
      "label": "Transform Yourself",
      "index": 150,
      "video_id": "VyIUAyvih28"
    },
    {
      "id": "episode:iQ5XwLslkVY",
      "type": "episode",
      "label": "Thriving with AI at Work and in Life.",
      "index": 151,
      "video_id": "iQ5XwLslkVY"
    },
    {
      "id": "episode:gL8rNVaCo1w",
      "type": "episode",
      "label": "KZAK Endorses The Human Workforce Podcast Series",
      "index": 152,
      "video_id": "gL8rNVaCo1w"
    },
    {
      "id": "episode:dGzO4UjaJGw",
      "type": "episode",
      "label": "Don't leave work without The Human Workforce.",
      "index": 153,
      "video_id": "dGzO4UjaJGw"
    },
    {
      "id": "episode:12EsnHgZv3A",
      "type": "episode",
      "label": "Control your own AI",
      "index": 154,
      "video_id": "12EsnHgZv3A"
    },
    {
      "id": "episode:h9kzFqWObwc",
      "type": "episode",
      "label": "I am not an AI, I am a Human!",
      "index": 155,
      "video_id": "h9kzFqWObwc"
    },
    {
      "id": "episode:Xg3SLukLw-M",
      "type": "episode",
      "label": "Breaking News from The Human Workforce",
      "index": 156,
      "video_id": "Xg3SLukLw-M"
    },
    {
      "id": "episode:wf93FdfCSUw",
      "type": "episode",
      "label": "Thrive in the age of AI",
      "index": 157,
      "video_id": "wf93FdfCSUw"
    },
    {
      "id": "episode:I3--Bac_6Cw",
      "type": "episode",
      "label": "The Human Workforce, where humans drive the bus.",
      "index": 158,
      "video_id": "I3--Bac_6Cw"
    },
    {
      "id": "episode:fpOFPHPIDUA",
      "type": "episode",
      "label": "New Book,  The Agentic Insider - July 2026",
      "index": 159,
      "video_id": "fpOFPHPIDUA"
    },
    {
      "id": "episode:qtABWs8updY",
      "type": "episode",
      "label": "Human Wisdom Matters More in the Age of AI",
      "index": 160,
      "video_id": "qtABWs8updY"
    },
    {
      "id": "episode:Qwp8KpXVt04",
      "type": "episode",
      "label": "Checkout The Human Workforce",
      "index": 161,
      "video_id": "Qwp8KpXVt04"
    },
    {
      "id": "episode:KEn2EDFl-eQ",
      "type": "episode",
      "label": "New Book Coming in July 2026, The Agentic Insider.",
      "index": 162,
      "video_id": "KEn2EDFl-eQ"
    },
    {
      "id": "episode:zYvbgp5n_vg",
      "type": "episode",
      "label": "Use AI as a Teammate, not an Enemy.",
      "index": 163,
      "video_id": "zYvbgp5n_vg"
    },
    {
      "id": "episode:iE6CaCswpS0",
      "type": "episode",
      "label": "Check out the Podcasts on The Human Workforce",
      "index": 164,
      "video_id": "iE6CaCswpS0"
    },
    {
      "id": "episode:U43XW09bys4",
      "type": "episode",
      "label": "Dont Leave Work Without The Human Workforce",
      "index": 165,
      "video_id": "U43XW09bys4"
    },
    {
      "id": "episode:smRqKqgcFnA",
      "type": "episode",
      "label": "New Book - The Human Disadvantage",
      "index": 166,
      "video_id": "smRqKqgcFnA"
    },
    {
      "id": "episode:gABVU6S5Yuo",
      "type": "episode",
      "label": "The Human Workforce - Wisdom is Rare",
      "index": 167,
      "video_id": "gABVU6S5Yuo"
    },
    {
      "id": "episode:kgfqUdMTGZ0",
      "type": "episode",
      "label": "Expert Insights on The Human Workforce Podcast",
      "index": 168,
      "video_id": "kgfqUdMTGZ0"
    },
    {
      "id": "episode:zMX_cTe9BT4",
      "type": "episode",
      "label": "How to Future-Proof Your Career Against AI",
      "index": 169,
      "video_id": "zMX_cTe9BT4"
    },
    {
      "id": "episode:Qjx6VlR8v1o",
      "type": "episode",
      "label": "AI Won't Replace You. But This Might.",
      "index": 170,
      "video_id": "Qjx6VlR8v1o"
    },
    {
      "id": "episode:qN_RvW8-uoI",
      "type": "episode",
      "label": "The Human Advantage in an AI Economy",
      "index": 171,
      "video_id": "qN_RvW8-uoI"
    },
    {
      "id": "episode:20GUMXxiT90",
      "type": "episode",
      "label": "The Career Survival Guide for the Age of AI",
      "index": 172,
      "video_id": "20GUMXxiT90"
    },
    {
      "id": "episode:RPtRYaR9luo",
      "type": "episode",
      "label": "Checkout the human workforce podcast series",
      "index": 173,
      "video_id": "RPtRYaR9luo"
    },
    {
      "id": "episode:TF5LGT--SH8",
      "type": "episode",
      "label": "Order The Human Disadvantage - Book       #books",
      "index": 174,
      "video_id": "TF5LGT--SH8"
    },
    {
      "id": "episode:_GiAI9stH7s",
      "type": "episode",
      "label": "Checkout The Human Workforce Podcast",
      "index": 175,
      "video_id": "_GiAI9stH7s"
    },
    {
      "id": "episode:dBH7bYLY_vk",
      "type": "episode",
      "label": "The Human Workforce Podcast Information - Subscribe Today",
      "index": 176,
      "video_id": "dBH7bYLY_vk"
    },
    {
      "id": "episode:iGZW5P0LnC8",
      "type": "episode",
      "label": "The Human Workforce Information",
      "index": 177,
      "video_id": "iGZW5P0LnC8"
    },
    {
      "id": "episode:NqVuxvUQS_U",
      "type": "episode",
      "label": "Your Human Potential",
      "index": 178,
      "video_id": "NqVuxvUQS_U"
    },
    {
      "id": "episode:-m1bNLvkQXA",
      "type": "episode",
      "label": "The Hidden Skill AI Can\u2019t Replace",
      "index": 179,
      "video_id": "-m1bNLvkQXA"
    },
    {
      "id": "episode:mUaVultbrHk",
      "type": "episode",
      "label": "The Human Disadvantage  - New Book, Now Available",
      "index": 180,
      "video_id": "mUaVultbrHk"
    },
    {
      "id": "episode:pleXqB0kqQc",
      "type": "episode",
      "label": "The Career Advice Nobody Is Giving",
      "index": 181,
      "video_id": "pleXqB0kqQc"
    },
    {
      "id": "episode:G3dcBK3U1xw",
      "type": "episode",
      "label": "The Human Workforce Podcast help define AI.",
      "index": 182,
      "video_id": "G3dcBK3U1xw"
    },
    {
      "id": "episode:705wfqD27CQ",
      "type": "episode",
      "label": "Humans Define Work",
      "index": 183,
      "video_id": "705wfqD27CQ"
    },
    {
      "id": "episode:RClgb3bcmhg",
      "type": "episode",
      "label": "Understanding AI in the Modern Workforce",
      "index": 184,
      "video_id": "RClgb3bcmhg"
    },
    {
      "id": "episode:iJBkSb1Luns",
      "type": "episode",
      "label": "Human Workforce with AI",
      "index": 185,
      "video_id": "iJBkSb1Luns"
    },
    {
      "id": "episode:3vODeyNSnOQ",
      "type": "episode",
      "label": "Honor of Memorial Day",
      "index": 186,
      "video_id": "3vODeyNSnOQ"
    },
    {
      "id": "episode:pxSq38VWjC8",
      "type": "episode",
      "label": "Understanding AI",
      "index": 187,
      "video_id": "pxSq38VWjC8"
    },
    {
      "id": "episode:SYRkP0qTFTM",
      "type": "episode",
      "label": "Honoring Memorial Day",
      "index": 188,
      "video_id": "SYRkP0qTFTM"
    },
    {
      "id": "episode:zgF2KHhBVoo",
      "type": "episode",
      "label": "The AI Work Advantage",
      "index": 189,
      "video_id": "zgF2KHhBVoo"
    },
    {
      "id": "episode:HDXPbgBvhIE",
      "type": "episode",
      "label": "AI with less stress.",
      "index": 190,
      "video_id": "HDXPbgBvhIE"
    },
    {
      "id": "episode:daHAnK6JJ28",
      "type": "episode",
      "label": "AI's Essence of Work is Shifting",
      "index": 191,
      "video_id": "daHAnK6JJ28"
    },
    {
      "id": "episode:E0wKFjVR_0I",
      "type": "episode",
      "label": "Automation is not the Enemy!",
      "index": 192,
      "video_id": "E0wKFjVR_0I"
    },
    {
      "id": "episode:gIZUw45R-kQ",
      "type": "episode",
      "label": "The Human Workforce Insights.",
      "index": 193,
      "video_id": "gIZUw45R-kQ"
    },
    {
      "id": "episode:mqtWdDGzjCQ",
      "type": "episode",
      "label": "Humans Define Work",
      "index": 194,
      "video_id": "mqtWdDGzjCQ"
    },
    {
      "id": "episode:zj98MPWYmCI",
      "type": "episode",
      "label": "Short Video on the human workforce",
      "index": 195,
      "video_id": "zj98MPWYmCI"
    },
    {
      "id": "episode:afsP1GkSOPI",
      "type": "episode",
      "label": "The Last Job You'll Ever Hate",
      "index": 196,
      "video_id": "afsP1GkSOPI"
    },
    {
      "id": "concept:people:simon carber",
      "type": "concept",
      "category": "people",
      "label": "simon carber",
      "episode_count": 1
    },
    {
      "id": "concept:people:lochlan reed",
      "type": "concept",
      "category": "people",
      "label": "lochlan reed",
      "episode_count": 2
    },
    {
      "id": "concept:people:lara rowan croft",
      "type": "concept",
      "category": "people",
      "label": "lara rowan croft",
      "episode_count": 1
    },
    {
      "id": "concept:people:jim cavallo",
      "type": "concept",
      "category": "people",
      "label": "jim cavallo",
      "episode_count": 1
    },
    {
      "id": "concept:organizations:goldman sachs",
      "type": "concept",
      "category": "organizations",
      "label": "goldman sachs",
      "episode_count": 1
    },
    {
      "id": "concept:platforms:youtube",
      "type": "concept",
      "category": "platforms",
      "label": "youtube",
      "episode_count": 2
    },
    {
      "id": "concept:concepts:ai infrastructure",
      "type": "concept",
      "category": "concepts",
      "label": "ai infrastructure",
      "episode_count": 1
    },
    {
      "id": "concept:concepts:data centers",
      "type": "concept",
      "category": "concepts",
      "label": "data centers",
      "episode_count": 1
    },
    {
      "id": "concept:concepts:ai hallucination",
      "type": "concept",
      "category": "concepts",
      "label": "ai hallucination",
      "episode_count": 1
    },
    {
      "id": "concept:concepts:economic efficiency",
      "type": "concept",
      "category": "concepts",
      "label": "economic efficiency",
      "episode_count": 1
    },
    {
      "id": "concept:concepts:operational efficiency",
      "type": "concept",
      "category": "concepts",
      "label": "operational efficiency",
      "episode_count": 1
    },
    {
      "id": "concept:concepts:ai theater",
      "type": "concept",
      "category": "concepts",
      "label": "ai theater",
      "episode_count": 1
    },
    {
      "id": "concept:concepts:human control layer",
      "type": "concept",
      "category": "concepts",
      "label": "human control layer",
      "episode_count": 1
    },
    {
      "id": "concept:concepts:workflow engineering",
      "type": "concept",
      "category": "concepts",
      "label": "workflow engineering",
      "episode_count": 1
    },
    {
      "id": "concept:concepts:labor replacement",
      "type": "concept",
      "category": "concepts",
      "label": "labor replacement",
      "episode_count": 1
    },
    {
      "id": "concept:concepts:corporate paralysis",
      "type": "concept",
      "category": "concepts",
      "label": "corporate paralysis",
      "episode_count": 1
    },
    {
      "id": "concept:technologies:ai systems",
      "type": "concept",
      "category": "technologies",
      "label": "ai systems",
      "episode_count": 1
    },
    {
      "id": "concept:technologies:ai models",
      "type": "concept",
      "category": "technologies",
      "label": "ai models",
      "episode_count": 1
    },
    {
      "id": "concept:technologies:chips",
      "type": "concept",
      "category": "technologies",
      "label": "chips",
      "episode_count": 1
    },
    {
      "id": "concept:technologies:power grids",
      "type": "concept",
      "category": "technologies",
      "label": "power grids",
      "episode_count": 1
    },
    {
      "id": "concept:technologies:api calls",
      "type": "concept",
      "category": "technologies",
      "label": "api calls",
      "episode_count": 1
    },
    {
      "id": "concept:technologies:risk models",
      "type": "concept",
      "category": "technologies",
      "label": "risk models",
      "episode_count": 1
    },
    {
      "id": "concept:methodologies:quality assurance",
      "type": "concept",
      "category": "methodologies",
      "label": "quality assurance",
      "episode_count": 1
    },
    {
      "id": "concept:methodologies:governance",
      "type": "concept",
      "category": "methodologies",
      "label": "governance",
      "episode_count": 1
    },
    {
      "id": "concept:methodologies:data quality validation",
      "type": "concept",
      "category": "methodologies",
      "label": "data quality validation",
      "episode_count": 1
    },
    {
      "id": "concept:methodologies:risk management",
      "type": "concept",
      "category": "methodologies",
      "label": "risk management",
      "episode_count": 1
    },
    {
      "id": "concept:frameworks:human control layer",
      "type": "concept",
      "category": "frameworks",
      "label": "human control layer",
      "episode_count": 1
    },
    {
      "id": "concept:people:simon carver",
      "type": "concept",
      "category": "people",
      "label": "simon carver",
      "episode_count": 1
    },
    {
      "id": "concept:concepts:automation arms race",
      "type": "concept",
      "category": "concepts",
      "label": "automation arms race",
      "episode_count": 1
    },
    {
      "id": "concept:concepts:labor displacement",
      "type": "concept",
      "category": "concepts",
      "label": "labor displacement",
      "episode_count": 1
    },
    {
      "id": "concept:concepts:deadweight loss",
      "type": "concept",
      "category": "concepts",
      "label": "deadweight loss",
      "episode_count": 1
    },
    {
      "id": "concept:concepts:consumer demand",
      "type": "concept",
      "category": "concepts",
      "label": "consumer demand",
      "episode_count": 1
    },
    {
      "id": "concept:concepts:human dignity",
      "type": "concept",
      "category": "concepts",
      "label": "human dignity",
      "episode_count": 1
    },
    {
      "id": "concept:concepts:meaningful work",
      "type": "concept",
      "category": "concepts",
      "label": "meaningful work",
      "episode_count": 1
    },
    {
      "id": "concept:concepts:drudgery",
      "type": "concept",
      "category": "concepts",
      "label": "drudgery",
      "episode_count": 1
    },
    {
      "id": "concept:concepts:busywork",
      "type": "concept",
      "category": "concepts",
      "label": "busywork",
      "episode_count": 1
    },
    {
      "id": "concept:technologies:ai",
      "type": "concept",
      "category": "technologies",
      "label": "ai",
      "episode_count": 1
    },
    {
      "id": "concept:technologies:large language models",
      "type": "concept",
      "category": "technologies",
      "label": "large language models",
      "episode_count": 1
    },
    {
      "id": "concept:technologies:machine learning",
      "type": "concept",
      "category": "technologies",
      "label": "machine learning",
      "episode_count": 1
    },
    {
      "id": "concept:methodologies:management by spreadsheet",
      "type": "concept",
      "category": "methodologies",
      "label": "management by spreadsheet",
      "episode_count": 1
    },
    {
      "id": "concept:methodologies:redesign",
      "type": "concept",
      "category": "methodologies",
      "label": "redesign",
      "episode_count": 1
    },
    {
      "id": "concept:frameworks:ubi",
      "type": "concept",
      "category": "frameworks",
      "label": "ubi",
      "episode_count": 1
    },
    {
      "id": "concept:frameworks:upskilling",
      "type": "concept",
      "category": "frameworks",
      "label": "upskilling",
      "episode_count": 1
    },
    {
      "id": "topic:Generative AI",
      "type": "topic",
      "label": "Generative AI",
      "episode_count": 2
    },
    {
      "id": "topic:Future of Work",
      "type": "topic",
      "label": "Future of Work",
      "episode_count": 2
    },
    {
      "id": "topic:Enterprise Transformation",
      "type": "topic",
      "label": "Enterprise Transformation",
      "episode_count": 2
    },
    {
      "id": "topic:Automation",
      "type": "topic",
      "label": "Automation",
      "episode_count": 2
    },
    {
      "id": "topic:Digital Labor",
      "type": "topic",
      "label": "Digital Labor",
      "episode_count": 2
    },
    {
      "id": "topic:Human Skills",
      "type": "topic",
      "label": "Human Skills",
      "episode_count": 2
    },
    {
      "id": "topic:Governance",
      "type": "topic",
      "label": "Governance",
      "episode_count": 2
    },
    {
      "id": "topic:Risk Management",
      "type": "topic",
      "label": "Risk Management",
      "episode_count": 2
    },
    {
      "id": "topic:Leadership",
      "type": "topic",
      "label": "Leadership",
      "episode_count": 2
    },
    {
      "id": "topic:Organizational Design",
      "type": "topic",
      "label": "Organizational Design",
      "episode_count": 2
    },
    {
      "id": "topic:Operational Resilience",
      "type": "topic",
      "label": "Operational Resilience",
      "episode_count": 1
    },
    {
      "id": "topic:Productivity",
      "type": "topic",
      "label": "Productivity",
      "episode_count": 1
    }
  ],
  "edges": [
    {
      "source": "episode:YXxf_3euA8c",
      "target": "concept:people:simon carber",
      "relation": "mentions"
    },
    {
      "source": "episode:YXxf_3euA8c",
      "target": "concept:people:lochlan reed",
      "relation": "mentions"
    },
    {
      "source": "episode:_4Cayu-GHMc",
      "target": "concept:people:lochlan reed",
      "relation": "mentions"
    },
    {
      "source": "episode:YXxf_3euA8c",
      "target": "concept:people:lara rowan croft",
      "relation": "mentions"
    },
    {
      "source": "episode:YXxf_3euA8c",
      "target": "concept:people:jim cavallo",
      "relation": "mentions"
    },
    {
      "source": "episode:YXxf_3euA8c",
      "target": "concept:organizations:goldman sachs",
      "relation": "mentions"
    },
    {
      "source": "episode:YXxf_3euA8c",
      "target": "concept:platforms:youtube",
      "relation": "mentions"
    },
    {
      "source": "episode:_4Cayu-GHMc",
      "target": "concept:platforms:youtube",
      "relation": "mentions"
    },
    {
      "source": "episode:YXxf_3euA8c",
      "target": "concept:concepts:ai infrastructure",
      "relation": "mentions"
    },
    {
      "source": "episode:YXxf_3euA8c",
      "target": "concept:concepts:data centers",
      "relation": "mentions"
    },
    {
      "source": "episode:YXxf_3euA8c",
      "target": "concept:concepts:ai hallucination",
      "relation": "mentions"
    },
    {
      "source": "episode:YXxf_3euA8c",
      "target": "concept:concepts:economic efficiency",
      "relation": "mentions"
    },
    {
      "source": "episode:YXxf_3euA8c",
      "target": "concept:concepts:operational efficiency",
      "relation": "mentions"
    },
    {
      "source": "episode:YXxf_3euA8c",
      "target": "concept:concepts:ai theater",
      "relation": "mentions"
    },
    {
      "source": "episode:YXxf_3euA8c",
      "target": "concept:concepts:human control layer",
      "relation": "mentions"
    },
    {
      "source": "episode:YXxf_3euA8c",
      "target": "concept:concepts:workflow engineering",
      "relation": "mentions"
    },
    {
      "source": "episode:YXxf_3euA8c",
      "target": "concept:concepts:labor replacement",
      "relation": "mentions"
    },
    {
      "source": "episode:YXxf_3euA8c",
      "target": "concept:concepts:corporate paralysis",
      "relation": "mentions"
    },
    {
      "source": "episode:YXxf_3euA8c",
      "target": "concept:technologies:ai systems",
      "relation": "mentions"
    },
    {
      "source": "episode:YXxf_3euA8c",
      "target": "concept:technologies:ai models",
      "relation": "mentions"
    },
    {
      "source": "episode:YXxf_3euA8c",
      "target": "concept:technologies:chips",
      "relation": "mentions"
    },
    {
      "source": "episode:YXxf_3euA8c",
      "target": "concept:technologies:power grids",
      "relation": "mentions"
    },
    {
      "source": "episode:YXxf_3euA8c",
      "target": "concept:technologies:api calls",
      "relation": "mentions"
    },
    {
      "source": "episode:YXxf_3euA8c",
      "target": "concept:technologies:risk models",
      "relation": "mentions"
    },
    {
      "source": "episode:YXxf_3euA8c",
      "target": "concept:methodologies:quality assurance",
      "relation": "mentions"
    },
    {
      "source": "episode:YXxf_3euA8c",
      "target": "concept:methodologies:governance",
      "relation": "mentions"
    },
    {
      "source": "episode:YXxf_3euA8c",
      "target": "concept:methodologies:data quality validation",
      "relation": "mentions"
    },
    {
      "source": "episode:YXxf_3euA8c",
      "target": "concept:methodologies:risk management",
      "relation": "mentions"
    },
    {
      "source": "episode:YXxf_3euA8c",
      "target": "concept:frameworks:human control layer",
      "relation": "mentions"
    },
    {
      "source": "episode:_4Cayu-GHMc",
      "target": "concept:people:simon carver",
      "relation": "mentions"
    },
    {
      "source": "episode:_4Cayu-GHMc",
      "target": "concept:concepts:automation arms race",
      "relation": "mentions"
    },
    {
      "source": "episode:_4Cayu-GHMc",
      "target": "concept:concepts:labor displacement",
      "relation": "mentions"
    },
    {
      "source": "episode:_4Cayu-GHMc",
      "target": "concept:concepts:deadweight loss",
      "relation": "mentions"
    },
    {
      "source": "episode:_4Cayu-GHMc",
      "target": "concept:concepts:consumer demand",
      "relation": "mentions"
    },
    {
      "source": "episode:_4Cayu-GHMc",
      "target": "concept:concepts:human dignity",
      "relation": "mentions"
    },
    {
      "source": "episode:_4Cayu-GHMc",
      "target": "concept:concepts:meaningful work",
      "relation": "mentions"
    },
    {
      "source": "episode:_4Cayu-GHMc",
      "target": "concept:concepts:drudgery",
      "relation": "mentions"
    },
    {
      "source": "episode:_4Cayu-GHMc",
      "target": "concept:concepts:busywork",
      "relation": "mentions"
    },
    {
      "source": "episode:_4Cayu-GHMc",
      "target": "concept:technologies:ai",
      "relation": "mentions"
    },
    {
      "source": "episode:_4Cayu-GHMc",
      "target": "concept:technologies:large language models",
      "relation": "mentions"
    },
    {
      "source": "episode:_4Cayu-GHMc",
      "target": "concept:technologies:machine learning",
      "relation": "mentions"
    },
    {
      "source": "episode:_4Cayu-GHMc",
      "target": "concept:methodologies:management by spreadsheet",
      "relation": "mentions"
    },
    {
      "source": "episode:_4Cayu-GHMc",
      "target": "concept:methodologies:redesign",
      "relation": "mentions"
    },
    {
      "source": "episode:_4Cayu-GHMc",
      "target": "concept:frameworks:ubi",
      "relation": "mentions"
    },
    {
      "source": "episode:_4Cayu-GHMc",
      "target": "concept:frameworks:upskilling",
      "relation": "mentions"
    },
    {
      "source": "episode:YXxf_3euA8c",
      "target": "topic:Generative AI",
      "relation": "covers"
    },
    {
      "source": "episode:_4Cayu-GHMc",
      "target": "topic:Generative AI",
      "relation": "covers"
    },
    {
      "source": "episode:YXxf_3euA8c",
      "target": "topic:Future of Work",
      "relation": "covers"
    },
    {
      "source": "episode:_4Cayu-GHMc",
      "target": "topic:Future of Work",
      "relation": "covers"
    },
    {
      "source": "episode:YXxf_3euA8c",
      "target": "topic:Enterprise Transformation",
      "relation": "covers"
    },
    {
      "source": "episode:_4Cayu-GHMc",
      "target": "topic:Enterprise Transformation",
      "relation": "covers"
    },
    {
      "source": "episode:YXxf_3euA8c",
      "target": "topic:Automation",
      "relation": "covers"
    },
    {
      "source": "episode:_4Cayu-GHMc",
      "target": "topic:Automation",
      "relation": "covers"
    },
    {
      "source": "episode:YXxf_3euA8c",
      "target": "topic:Digital Labor",
      "relation": "covers"
    },
    {
      "source": "episode:_4Cayu-GHMc",
      "target": "topic:Digital Labor",
      "relation": "covers"
    },
    {
      "source": "episode:YXxf_3euA8c",
      "target": "topic:Human Skills",
      "relation": "covers"
    },
    {
      "source": "episode:_4Cayu-GHMc",
      "target": "topic:Human Skills",
      "relation": "covers"
    },
    {
      "source": "episode:YXxf_3euA8c",
      "target": "topic:Governance",
      "relation": "covers"
    },
    {
      "source": "episode:_4Cayu-GHMc",
      "target": "topic:Governance",
      "relation": "covers"
    },
    {
      "source": "episode:YXxf_3euA8c",
      "target": "topic:Risk Management",
      "relation": "covers"
    },
    {
      "source": "episode:_4Cayu-GHMc",
      "target": "topic:Risk Management",
      "relation": "covers"
    },
    {
      "source": "episode:YXxf_3euA8c",
      "target": "topic:Leadership",
      "relation": "covers"
    },
    {
      "source": "episode:_4Cayu-GHMc",
      "target": "topic:Leadership",
      "relation": "covers"
    },
    {
      "source": "episode:YXxf_3euA8c",
      "target": "topic:Organizational Design",
      "relation": "covers"
    },
    {
      "source": "episode:_4Cayu-GHMc",
      "target": "topic:Organizational Design",
      "relation": "covers"
    },
    {
      "source": "episode:_4Cayu-GHMc",
      "target": "topic:Operational Resilience",
      "relation": "covers"
    },
    {
      "source": "episode:_4Cayu-GHMc",
      "target": "topic:Productivity",
      "relation": "covers"
    },
    {
      "source": "episode:YXxf_3euA8c",
      "target": "episode:_4Cayu-GHMc",
      "relation": "related",
      "shared_topics": [
        "Automation",
        "Digital Labor",
        "Enterprise Transformation",
        "Future of Work",
        "Generative AI",
        "Governance",
        "Human Skills",
        "Leadership",
        "Organizational Design",
        "Risk Management"
      ]
    }
  ]
}